jaxvmas/__init__.py
jaxvmas/equinox_utils.py
jaxvmas/interactive_rendering.py
jaxvmas/make_env.py
jaxvmas/runner_script.py
jaxvmas/scenario/__init__.py
jaxvmas/scenario/football.py
jaxvmas/scenario/mpe/__init__.py
jaxvmas/scenario/mpe/simple.py
jaxvmas/scenario_data/road_traffic/road_traffic_cpm_lab.xml
jaxvmas/simulator/README
jaxvmas/simulator/__init__.py
jaxvmas/simulator/controllers/__init__.py
jaxvmas/simulator/controllers/velocity_controller.py
jaxvmas/simulator/core/__init__.py
jaxvmas/simulator/core/action.py
jaxvmas/simulator/core/agent.py
jaxvmas/simulator/core/entity.py
jaxvmas/simulator/core/jax_vectorized_object.py
jaxvmas/simulator/core/landmark.py
jaxvmas/simulator/core/ray_physics.py
jaxvmas/simulator/core/shapes.py
jaxvmas/simulator/core/states.py
jaxvmas/simulator/core/world.py
jaxvmas/simulator/dynamics/__init__.py
jaxvmas/simulator/dynamics/common.py
jaxvmas/simulator/dynamics/diff_drive.py
jaxvmas/simulator/dynamics/drone.py
jaxvmas/simulator/dynamics/forward.py
jaxvmas/simulator/dynamics/holonomic.py
jaxvmas/simulator/dynamics/holonomic_with_rot.py
jaxvmas/simulator/dynamics/kinematic_bicycle.py
jaxvmas/simulator/dynamics/rotation.py
jaxvmas/simulator/dynamics/static.py
jaxvmas/simulator/environment/__init__.py
jaxvmas/simulator/environment/environment.py
jaxvmas/simulator/environment/jaxgym/__init__.py
jaxvmas/simulator/environment/jaxgym/base.py
jaxvmas/simulator/environment/jaxgym/jaxgymnasium.py
jaxvmas/simulator/environment/jaxgym/jaxgymnasium_vec.py
jaxvmas/simulator/environment/jaxgym/spaces.py
jaxvmas/simulator/heuristic_policy.py
jaxvmas/simulator/joints.py
jaxvmas/simulator/physics.py
jaxvmas/simulator/rendering.py
jaxvmas/simulator/scenario.py
jaxvmas/simulator/secrcode.ttf
jaxvmas/simulator/sensors.py
jaxvmas/simulator/utils.py
jaxvmas-0.0.0.dist-info/LICENSE
jaxvmas-0.0.0.dist-info/METADATA
jaxvmas-0.0.0.dist-info/WHEEL
jaxvmas-0.0.0.dist-info/RECORD
