Metadata-Version: 2.3
Name: jaxvmas
Version: 0.0.0
Summary: JAX implementation of Vectorized Multi-Agent Simulator
License: GPLv3
Author: Joseph Selvaraj
Author-email: jdselvaraaj@gmail.com
Requires-Python: >=3.11,<4.0
Classifier: License :: Other/Proprietary License
Classifier: Programming Language :: Python :: 3
Classifier: Programming Language :: Python :: 3.11
Classifier: Programming Language :: Python :: 3.12
Classifier: Programming Language :: Python :: 3.13
Requires-Dist: jax
Project-URL: Repository, https://github.com/jselvaraaj/JaxVMAS
